py_123pan_client/__init__.py
py_123pan_client/client.py
py_123pan_client/consts.py
py_123pan_client/exceptions.py
py_123pan_client/integrations.py
py_123pan_client/models.py
py_123pan_client/utils.py
py_123pan_client-0.1.8.dist-info/METADATA
py_123pan_client-0.1.8.dist-info/WHEEL
py_123pan_client-0.1.8.dist-info/RECORD
