Metadata-Version: 2.4
Name: py-123pan-client
Version: 0.1.8
Summary: Unnoficial Python SDK for 123Pan Open Platform
Requires-Python: >=3.9
Requires-Dist: httpx>=0.27.0
Requires-Dist: pydantic
Provides-Extra: dagster
Requires-Dist: dagster>=1.10.0; extra == 'dagster'
